aih_django/__init__.py
aih_django/mixins/__init__.py
aih_django/mixins/custom_serializer_mixin.py
aih_django/mixins/permission_action_mixin.py
aih_django/mixins/permission_check_mixin.py
aih_django/mixins/permission_decorator_mixin.py
aih_django/models/__init__.py
aih_django/models/base_model.py
aih_django-0.0.6.dist-info/METADATA
aih_django-0.0.6.dist-info/WHEEL
aih_django-0.0.6.dist-info/top_level.txt
aih_django-0.0.6.dist-info/RECORD
