Metadata-Version: 2.1
Name: aih-django
Version: 0.0.6
Summary: A collection of Django utilities
Home-page: https://github.com/AI-Heroes/aih-django/tree/0.0.1
Author: Joseph
Author-email: joseph@aiheroes.io
License: UNKNOWN
Platform: UNKNOWN
Classifier: Framework :: Django
Classifier: Programming Language :: Python :: 3
Classifier: License :: OSI Approved :: MIT License
Classifier: Operating System :: OS Independent
Requires-Python: >=3.6
Requires-Dist: Django >=3.2
